README.md
aes_encryption_tool.py
setup.py
aes_encryption_tool.egg-info/PKG-INFO
aes_encryption_tool.egg-info/SOURCES.txt
aes_encryption_tool.egg-info/dependency_links.txt
aes_encryption_tool.egg-info/entry_points.txt
aes_encryption_tool.egg-info/requires.txt
aes_encryption_tool.egg-info/top_level.txt