Metadata-Version: 2.1
Name: aes-encryption-tool
Version: 1.0.1
Summary: AES Encryption/Decryption Tool with PyQt5 GUI
Home-page: https://github.com/syahra712/aes-encryption
Author: SYED AHNAF RAZA
Author-email: syahra2014@gmail.com
Classifier: Programming Language :: Python :: 3
Classifier: License :: OSI Approved :: MIT License
Classifier: Operating System :: OS Independent
Requires-Python: >=3.8
Requires-Dist: PyQt5
Requires-Dist: cryptography
